wildcard.hps-1.4.6-py2.7-nspkg.pth
wildcard/hps/__init__.py
wildcard/hps/brain.py
wildcard/hps/configure.zcml
wildcard/hps/hook.py
wildcard/hps/indexes.py
wildcard/hps/interfaces.py
wildcard/hps/mapping.py
wildcard/hps/opensearch.py
wildcard/hps/patches.py
wildcard/hps/query.py
wildcard/hps/testing.py
wildcard/hps/utils.py
wildcard/hps/browser/__init__.py
wildcard/hps/browser/configure.zcml
wildcard/hps/browser/controlpanel.py
wildcard/hps/browser/controlpanel_layout.pt
wildcard/hps/browser/search.py
wildcard/hps/browser/utilviews.py
wildcard/hps/profiles/default/browserlayer.xml
wildcard/hps/profiles/default/controlpanel.xml
wildcard/hps/profiles/default/metadata.xml
wildcard/hps/profiles/default/registry.xml
wildcard/hps/scripts/__init__.py
wildcard/hps/scripts/reindex.py
wildcard/hps/tests/__init__.py
wildcard/hps/tests/test_catalog.py
wildcard/hps/tests/test_search.py
wildcard.hps-1.4.6.dist-info/LICENSE.GPL
wildcard.hps-1.4.6.dist-info/METADATA
wildcard.hps-1.4.6.dist-info/WHEEL
wildcard.hps-1.4.6.dist-info/entry_points.txt
wildcard.hps-1.4.6.dist-info/namespace_packages.txt
wildcard.hps-1.4.6.dist-info/top_level.txt
wildcard.hps-1.4.6.dist-info/RECORD
