Metadata-Version: 2.1
Name: wildcard.hps
Version: 1.4.6
Summary: opensearch integration with CastleCMS and Plone
Home-page: https://github.com/castlecms/wildcard.hps
Author: Wildcard Corp.
Author-email: corporate@wildcardcorp.com
License: GPL version 2
Project-URL: Source, https://github.com/castlecms/wildcard.hps
Project-URL: Tracker, https://github.com/castlecms/wildcard.hps/issues
Project-URL: PyPI, https://pypi.python.org/pypi/wildcard.hps
Keywords: castlecms plone opensearch search indexing
Platform: UNKNOWN
Classifier: Environment :: Web Environment
Classifier: Development Status :: 5 - Production/Stable
Classifier: Framework :: Plone
Classifier: Framework :: Plone :: Addon
Classifier: Framework :: Plone :: 5.0
Classifier: Framework :: Plone :: 5.1
Classifier: Programming Language :: Python
Classifier: Programming Language :: Python :: 2.7
Classifier: Programming Language :: Python :: 3.7
Classifier: Operating System :: OS Independent
Classifier: License :: OSI Approved :: GNU General Public License v2 (GPLv2)
Requires-Python: >2.7, !=3.0.*, !=3.1.*, !=3.2.*, !=3.3.*, !=3.4.*, !=3.5.*, !=3.6.*
Requires-Dist: setuptools
Requires-Dist: opensearch-py
Requires-Dist: plone.app.registry
Requires-Dist: plone.api
Provides-Extra: test
Requires-Dist: plone.app.contentrules ; extra == 'test'
Requires-Dist: plone.app.testing ; extra == 'test'
Requires-Dist: plone.testing (>=5.0.0) ; extra == 'test'
Requires-Dist: Products.ATContentTypes ; extra == 'test'
Requires-Dist: unittest2 ; extra == 'test'
